[{"oq":"0","q":"7250","rvnm":"长江","stcd":"60105400","stnm":"寸滩","tm":1621594800000,"wptn":"5","z":"161.68"},{"oq":"0","q":"3150","rvnm":"乌江","stcd":"60803000","stnm":"武隆","tm":1621594800000,"wptn":"5","z":"177.02"},{"oq":"0","q":"17600","rvnm":"长江","stcd":"60107300","stnm":"宜昌","tm":1621594800000,"wptn":"5","z":"44.23"},{"oq":"0","q":"15200","rvnm":"长江","stcd":"60108300","stnm":"沙市","tm":1621594800000,"wptn":"4","z":"36.03"},{"oq":"0","q":"0","rvnm":"长江","stcd":"60111200","stnm":"城陵矶(莲)","tm":1621594800000,"wptn":"5","z":"29.81"},{"oq":"0","q":"38000","rvnm":"长江","stcd":"60112200","stnm":"汉口","tm":1621594800000,"wptn":"5","z":"23.39"},{"oq":"0","q":"37400","rvnm":"长江","stcd":"60113400","stnm":"九江","tm":1621594800000,"wptn":"5","z":"17.134"},{"oq":"0","q":"44200","rvnm":"长江","stcd":"60115000","stnm":"大通","tm":1621594800000,"wptn":"5","z":"11.31"},{"oq":"0","q":"23100","rvnm":"洞庭湖","stcd":"61512000","stnm":"城陵矶(七)","tm":1621594800000,"wptn":"5","z":"30"},{"oq":"0","q":"8710","rvnm":"鄱阳湖","stcd":"62601600","stnm":"湖口","tm":1621594800000,"wptn":"5","z":"16.6"},{"oq":"0","q":"0","rvnm":"长江","stcd":"60107000","stnm":"茅坪(二)","tm":1621594800000,"wptn":"4","z":"152.353"},{"oq":"18400","q":"0","rvnm":"长江","stcd":"60106980","stnm":"三峡水库","tm":1621594800000,"wptn":"4","z":"152.35"},{"oq":"0","q":"0","rvnm":"汉江","stcd":"61802500","stnm":"龙王庙","tm":1621594800000,"wptn":"6","z":"160.79"},{"oq":"1670","q":"0","rvnm":"汉江","stcd":"61802700","stnm":"丹江口水库","tm":1621594800000,"wptn":"6","z":"160.79"}]