[{"oq":"0","q":"4370","rvnm":"长江","stcd":"60105400","stnm":"寸滩","tm":1615856400000,"wptn":"4","z":"166.07"},{"oq":"0","q":"830","rvnm":"乌江","stcd":"60803000","stnm":"武隆","tm":1615856400000,"wptn":"4","z":"170.75"},{"oq":"0","q":"6520","rvnm":"长江","stcd":"60107300","stnm":"宜昌","tm":1615856400000,"wptn":"6","z":"39.64"},{"oq":"0","q":"6860","rvnm":"长江","stcd":"60108300","stnm":"沙市","tm":1615856400000,"wptn":"4","z":"30.24"},{"oq":"0","q":"0","rvnm":"长江","stcd":"60111200","stnm":"城陵矶(莲)","tm":1615856400000,"wptn":"4","z":"23.25"},{"oq":"0","q":"17000","rvnm":"长江","stcd":"60112200","stnm":"汉口","tm":1615856400000,"wptn":"6","z":"16.95"},{"oq":"0","q":"17100","rvnm":"长江","stcd":"60113400","stnm":"九江","tm":1615856400000,"wptn":"5","z":"11.4"},{"oq":"0","q":"21300","rvnm":"长江","stcd":"60115000","stnm":"大通","tm":1615856400000,"wptn":"4","z":"6.93"},{"oq":"0","q":"8720","rvnm":"洞庭湖","stcd":"61512000","stnm":"城陵矶(七)","tm":1615856400000,"wptn":"4","z":"23.32"},{"oq":"0","q":"3910","rvnm":"鄱阳湖","stcd":"62601600","stnm":"湖口","tm":1615856400000,"wptn":"5","z":"10.63"},{"oq":"0","q":"0","rvnm":"长江","stcd":"60107000","stnm":"茅坪(二)","tm":1615856400000,"wptn":"6","z":"165.542"},{"oq":"6750","q":"0","rvnm":"长江","stcd":"60106980","stnm":"三峡水库","tm":1615856400000,"wptn":"6","z":"165.54"},{"oq":"0","q":"0","rvnm":"汉江","stcd":"61802500","stnm":"龙王庙","tm":1615856400000,"wptn":"6","z":"159.9"},{"oq":"806","q":"0","rvnm":"汉江","stcd":"61802700","stnm":"丹江口水库","tm":1615856400000,"wptn":"6","z":"159.9"}]