[{"oq":"0","q":"12600","rvnm":"长江","stcd":"60105400","stnm":"寸滩","tm":1657245600000,"wptn":"4","z":"165.15"},{"oq":"0","q":"1390","rvnm":"乌江","stcd":"60803000","stnm":"武隆","tm":1657245600000,"wptn":"5","z":"172.51"},{"oq":"0","q":"16100","rvnm":"长江","stcd":"60107300","stnm":"宜昌","tm":1657245600000,"wptn":"5","z":"43.54"},{"oq":"0","q":"14400","rvnm":"长江","stcd":"60108300","stnm":"沙市","tm":1657245600000,"wptn":"4","z":"36.19"},{"oq":"0","q":"0","rvnm":"长江","stcd":"60111200","stnm":"城陵矶(莲)","tm":1657245600000,"wptn":"5","z":"30.47"},{"oq":"0","q":"38100","rvnm":"长江","stcd":"60112200","stnm":"汉口","tm":1657245600000,"wptn":"4","z":"24.36"},{"oq":"0","q":"39800","rvnm":"长江","stcd":"60113400","stnm":"九江","tm":1657245600000,"wptn":"5","z":"18.085"},{"oq":"0","q":"49900","rvnm":"长江","stcd":"60115000","stnm":"大通","tm":1657245600000,"wptn":"6","z":"12.13"},{"oq":"0","q":"20100","rvnm":"洞庭湖","stcd":"61512000","stnm":"城陵矶(七)","tm":1657245600000,"wptn":"5","z":"30.6"},{"oq":"0","q":"9150","rvnm":"鄱阳湖","stcd":"62601600","stnm":"湖口","tm":1657245600000,"wptn":"6","z":"17.53"},{"oq":"0","q":"0","rvnm":"长江","stcd":"60107000","stnm":"茅坪(二)","tm":1657245600000,"wptn":"4","z":"146.58"},{"oq":"18700","q":"0","rvnm":"长江","stcd":"60106980","stnm":"三峡水库","tm":1657245600000,"wptn":"4","z":"146.58"},{"oq":"0","q":"0","rvnm":"汉江","stcd":"61802500","stnm":"龙王庙","tm":1657245600000,"wptn":"4","z":"158.32"},{"oq":"871","q":"264","rvnm":"汉江","stcd":"61802700","stnm":"丹江口水库","tm":1657245600000,"wptn":"4","z":"158.32"}]