[{"oq":"0","q":"15400","rvnm":"长江","stcd":"60105400","stnm":"寸滩","tm":1657857600000,"wptn":"4","z":"166.59"},{"oq":"0","q":"977","rvnm":"乌江","stcd":"60803000","stnm":"武隆","tm":1657854000000,"wptn":"4","z":"171.21"},{"oq":"0","q":"17700","rvnm":"长江","stcd":"60107300","stnm":"宜昌","tm":1657857600000,"wptn":"4","z":"44.11"},{"oq":"0","q":"14000","rvnm":"长江","stcd":"60108300","stnm":"沙市","tm":1657857600000,"wptn":"4","z":"35.02"},{"oq":"0","q":"0","rvnm":"长江","stcd":"60111200","stnm":"城陵矶(莲)","tm":1657857600000,"wptn":"6","z":"28.36"},{"oq":"0","q":"31500","rvnm":"长江","stcd":"60112200","stnm":"汉口","tm":1657857600000,"wptn":"4","z":"22.59"},{"oq":"0","q":"32900","rvnm":"长江","stcd":"60113400","stnm":"九江","tm":1657857600000,"wptn":"4","z":"17"},{"oq":"0","q":"44400","rvnm":"长江","stcd":"60115000","stnm":"大通","tm":1657857600000,"wptn":"4","z":"11.46"},{"oq":"0","q":"13600","rvnm":"洞庭湖","stcd":"61512000","stnm":"城陵矶(七)","tm":1657857600000,"wptn":"4","z":"28.43"},{"oq":"0","q":"8830","rvnm":"鄱阳湖","stcd":"62601600","stnm":"湖口","tm":1657857600000,"wptn":"6","z":"16.49"},{"oq":"0","q":"0","rvnm":"长江","stcd":"60107000","stnm":"茅坪(二)","tm":1657857600000,"wptn":"5","z":"146.36"},{"oq":"15500","q":"0","rvnm":"长江","stcd":"60106980","stnm":"三峡水库","tm":1657857600000,"wptn":"5","z":"146.36"},{"oq":"0","q":"0","rvnm":"汉江","stcd":"61802500","stnm":"龙王庙","tm":1657857600000,"wptn":"4","z":"158"},{"oq":"926","q":"457","rvnm":"汉江","stcd":"61802700","stnm":"丹江口水库","tm":1657857600000,"wptn":"4","z":"158"}]