[{"oq":"0","q":"16800","rvnm":"长江","stcd":"60105400","stnm":"寸滩","tm":1658062800000,"wptn":"5","z":"167.17"},{"oq":"0","q":"1920","rvnm":"乌江","stcd":"60803000","stnm":"武隆","tm":1658062800000,"wptn":"4","z":"173.97"},{"oq":"0","q":"19000","rvnm":"长江","stcd":"60107300","stnm":"宜昌","tm":1658062800000,"wptn":"4","z":"44.59"},{"oq":"0","q":"14800","rvnm":"长江","stcd":"60108300","stnm":"沙市","tm":1658062800000,"wptn":"5","z":"35.34"},{"oq":"0","q":"0","rvnm":"长江","stcd":"60111200","stnm":"城陵矶(莲)","tm":1658062800000,"wptn":"4","z":"27.77"},{"oq":"0","q":"29600","rvnm":"长江","stcd":"60112200","stnm":"汉口","tm":1658062800000,"wptn":"4","z":"22.07"},{"oq":"0","q":"29800","rvnm":"长江","stcd":"60113400","stnm":"九江","tm":1658062800000,"wptn":"6","z":"16.45"},{"oq":"0","q":"42500","rvnm":"长江","stcd":"60115000","stnm":"大通","tm":1658062800000,"wptn":"4","z":"11.18"},{"oq":"0","q":"12700","rvnm":"洞庭湖","stcd":"61512000","stnm":"城陵矶(七)","tm":1658062800000,"wptn":"6","z":"27.81"},{"oq":"0","q":"9690","rvnm":"鄱阳湖","stcd":"62601600","stnm":"湖口","tm":1658062800000,"wptn":"5","z":"15.94"},{"oq":"0","q":"0","rvnm":"长江","stcd":"60107000","stnm":"茅坪(二)","tm":1658062800000,"wptn":"4","z":"146.18"},{"oq":"21500","q":"0","rvnm":"长江","stcd":"60106980","stnm":"三峡水库","tm":1658062800000,"wptn":"4","z":"146.18"},{"oq":"0","q":"0","rvnm":"汉江","stcd":"61802500","stnm":"龙王庙","tm":1658062800000,"wptn":"6","z":"157.91"},{"oq":"817","q":"230","rvnm":"汉江","stcd":"61802700","stnm":"丹江口水库","tm":1658062800000,"wptn":"6","z":"157.91"}]