[{"oq":"0","q":"10500","rvnm":"长江","stcd":"60105400","stnm":"寸滩","tm":1649880000000,"wptn":"5","z":"166.96"},{"oq":"0","q":"1010","rvnm":"乌江","stcd":"60803000","stnm":"武隆","tm":1649880000000,"wptn":"4","z":"171.31"},{"oq":"0","q":"12500","rvnm":"长江","stcd":"60107300","stnm":"宜昌","tm":1649880000000,"wptn":"4","z":"42.16"},{"oq":"0","q":"11900","rvnm":"长江","stcd":"60108300","stnm":"沙市","tm":1649880000000,"wptn":"5","z":"33.09"},{"oq":"0","q":"0","rvnm":"长江","stcd":"60111200","stnm":"城陵矶(莲)","tm":1649880000000,"wptn":"5","z":"23.79"},{"oq":"0","q":"17200","rvnm":"长江","stcd":"60112200","stnm":"汉口","tm":1649880000000,"wptn":"6","z":"17.61"},{"oq":"0","q":"19200","rvnm":"长江","stcd":"60113400","stnm":"九江","tm":1649880000000,"wptn":"4","z":"12.44"},{"oq":"0","q":"24600","rvnm":"长江","stcd":"60115000","stnm":"大通","tm":1649880000000,"wptn":"6","z":"7.94"},{"oq":"0","q":"6250","rvnm":"洞庭湖","stcd":"61512000","stnm":"城陵矶(七)","tm":1649880000000,"wptn":"5","z":"23.84"},{"oq":"0","q":"6170","rvnm":"鄱阳湖","stcd":"62601600","stnm":"湖口","tm":1649880000000,"wptn":"5","z":"11.82"},{"oq":"0","q":"0","rvnm":"长江","stcd":"60107000","stnm":"茅坪(二)","tm":1649880000000,"wptn":"5","z":"164.77"},{"oq":"11200","q":"0","rvnm":"长江","stcd":"60106980","stnm":"三峡水库","tm":1649880000000,"wptn":"5","z":"164.77"},{"oq":"0","q":"0","rvnm":"汉江","stcd":"61802500","stnm":"龙王庙","tm":1649880000000,"wptn":"4","z":"161.95"},{"oq":"1360","q":"304","rvnm":"汉江","stcd":"61802700","stnm":"丹江口水库","tm":1649880000000,"wptn":"4","z":"161.95"}]