[{"oq":"0","q":"6390","rvnm":"长江","stcd":"60105400","stnm":"寸滩","tm":1663221600000,"wptn":"4","z":"160.84"},{"oq":"0","q":"409","rvnm":"乌江","stcd":"60803000","stnm":"武隆","tm":1663221600000,"wptn":"5","z":"169.36"},{"oq":"0","q":"9650","rvnm":"长江","stcd":"60107300","stnm":"宜昌","tm":1663221600000,"wptn":"5","z":"41.02"},{"oq":"0","q":"8590","rvnm":"长江","stcd":"60108300","stnm":"沙市","tm":1663221600000,"wptn":"4","z":"30.99"},{"oq":"0","q":"0","rvnm":"长江","stcd":"60111200","stnm":"城陵矶(莲)","tm":1663221600000,"wptn":"6","z":"20.2"},{"oq":"0","q":"10500","rvnm":"长江","stcd":"60112200","stnm":"汉口","tm":1663221600000,"wptn":"5","z":"13.5"},{"oq":"0","q":"10600","rvnm":"长江","stcd":"60113400","stnm":"九江","tm":1663221600000,"wptn":"6","z":"8.55"},{"oq":"0","q":"11400","rvnm":"长江","stcd":"60115000","stnm":"大通","tm":1663221600000,"wptn":"5","z":"5.24"},{"oq":"0","q":"1670","rvnm":"洞庭湖","stcd":"61512000","stnm":"城陵矶(七)","tm":1663221600000,"wptn":"6","z":"20.21"},{"oq":"0","q":"556","rvnm":"鄱阳湖","stcd":"62601600","stnm":"湖口","tm":1663221600000,"wptn":"4","z":"7.49"},{"oq":"0","q":"0","rvnm":"长江","stcd":"60107000","stnm":"茅坪(二)","tm":1663221600000,"wptn":"6","z":"146.75"},{"oq":"9800","q":"6900","rvnm":"长江","stcd":"60106980","stnm":"三峡水库","tm":1663221600000,"wptn":"6","z":"146.75"},{"oq":"0","q":"0","rvnm":"汉江","stcd":"61802500","stnm":"龙王庙","tm":1663214400000,"wptn":"6","z":"156.68"},{"oq":"648","q":"395","rvnm":"汉江","stcd":"61802700","stnm":"丹江口水库","tm":1663218000000,"wptn":"6","z":"156.68"}]